tdk/tdk/__init__.py
tdk/tdk/alphabet.py
tdk/tdk/dictionaries/__init__.py
tdk/tdk/dictionaries/ads.py
tdk/tdk/dictionaries/bati.py
tdk/tdk/dictionaries/bst.py
tdk/tdk/dictionaries/derleme.py
tdk/tdk/dictionaries/etj.py
tdk/tdk/dictionaries/etms.py
tdk/tdk/dictionaries/gts.py
tdk/tdk/dictionaries/kisi.py
tdk/tdk/dictionaries/lehce.py
tdk/tdk/dictionaries/sks.py
tdk/tdk/dictionaries/syyd.py
tdk/tdk/dictionaries/ts.py
tdk/tdk/dictionaries/yazim.py
tdk/tdk/dictionaries/ysk.py
tdk/tdk/enums.py
tdk/tdk/home.py
tdk/tdk/internal/__init__.py
tdk/tdk/internal/http.py
tdk/tdk/internal/utils.py
tdk/tdk/tools.py
tdk_py-2.0.0.dist-info/LICENSE
tdk_py-2.0.0.dist-info/METADATA
tdk_py-2.0.0.dist-info/WHEEL
tdk_py-2.0.0.dist-info/RECORD
