Metadata-Version: 2.3
Name: tdk-py
Version: 2.0.0
Summary: Python API for the Turkish Language Foundation
License: MIT
Keywords: tdk,turkish,language,nlp,api
Author: Emre Özcan
Author-email: emre@emreis.com
Requires-Python: >3.10
Classifier: Development Status :: 5 - Production/Stable
Classifier: Environment :: Console
Classifier: Intended Audience :: Developers
Classifier: Intended Audience :: Education
Classifier: Intended Audience :: Science/Research
Classifier: License :: OSI Approved :: MIT License
Classifier: Natural Language :: English
Classifier: Operating System :: OS Independent
Classifier: Programming Language :: Python
Classifier: Programming Language :: Python :: 3
Classifier: Programming Language :: Python :: 3.11
Classifier: Programming Language :: Python :: 3.12
Classifier: Programming Language :: Python :: 3.13
Classifier: Programming Language :: Python :: 3.10
Classifier: Topic :: Education
Classifier: Topic :: Scientific/Engineering
Classifier: Topic :: Software Development :: Libraries
Classifier: Topic :: Software Development :: Libraries :: Python Modules
Classifier: Topic :: Utilities
Requires-Dist: aiohttp (>=3.10.10,<4.0.0)
Requires-Dist: pydantic (>=2.9.2,<3.0.0)
Project-URL: Repository, https://github.com/emreozcan/tdk-py
